features/__init__.py
features/cohort.py
features/comparison.py
features/incidence_rate.py
interceptors/__init__.py
interceptors/auth.py
interceptors/base.py
pb/__init__.py
pb/clue_pb2.py
pb/clue_pb2_grpc.py
python_clue-0.2.0.dist-info/LICENSE
python_clue-0.2.0.dist-info/METADATA
python_clue-0.2.0.dist-info/WHEEL
python_clue-0.2.0.dist-info/top_level.txt
python_clue-0.2.0.dist-info/RECORD
