Metadata-Version: 2.1
Name: python-clue
Version: 0.2.0
Summary: Python interface to the MDwalks CLUE.
Home-page: https://github.com/linewalks/py-clue
Author: Linewalks
Author-email: jungwoo@linewalks.com
License: MIT
Platform: UNKNOWN
Requires-Python: >=3.8
Requires-Dist: grpcio
Requires-Dist: protobuf
